tedana_regressors/__init__.py
tedana_regressors/_version.py
tedana_regressors/tedana_regressors.py
tedana_regressors/utils.py
tedana_regressors-0.0.2.dist-info/LICENSE
tedana_regressors-0.0.2.dist-info/METADATA
tedana_regressors-0.0.2.dist-info/WHEEL
tedana_regressors-0.0.2.dist-info/entry_points.txt
tedana_regressors-0.0.2.dist-info/top_level.txt
tedana_regressors-0.0.2.dist-info/RECORD
